git_credential_netconf/__init__.py
git_credential_netconf/__main__.py
git_credential_netconf/netconf.py
git_credential_netconf-1.0.3.dist-info/LICENSE
git_credential_netconf-1.0.3.dist-info/METADATA
git_credential_netconf-1.0.3.dist-info/WHEEL
git_credential_netconf-1.0.3.dist-info/entry_points.txt
git_credential_netconf-1.0.3.dist-info/top_level.txt
git_credential_netconf-1.0.3.dist-info/RECORD
