Metadata-Version: 2.1
Name: git-credential-netconf
Version: 1.0.3
Summary: UNKNOWN
Home-page: https://github.com/arunanshub/git-credential-netconf
Author: Arunanshu Biswas
Author-email: mydellpc07@gmail.com
License: MIT
Platform: UNKNOWN
Classifier: Programming Language :: Python :: 3
Classifier: License :: OSI Approved :: MIT License
Classifier: Operating System :: OS Independent
Classifier: Intended Audience :: Developers
Requires-Dist: python-gnupg (>=0.4.7)
